{
    "pages": [
        {
            "chapter": 7,
            "verse": 105,
            "text": "allāhuvinṟe pēril satyamallāteānnuṁ paṟayātirikkān kaṭappeṭṭavanāṇ ñān. niṅṅaḷuṭe rakṣitāviṅkal ninnuḷḷa vyaktamāya teḷivuṁ keāṇṭāṇ ñān niṅṅaḷuṭe aṭutt vannirikkunnat‌. atināl isrāyīl santatikaḷe enṟe kūṭe ayakkū"
        },
        {
            "chapter": 7,
            "verse": 106,
            "text": "phir'aun paṟaññu: nī teḷivuṁ keāṇṭ tanneyāṇ vanniṭṭuḷḷateṅkil atiṅṅ keāṇṭuvā; nī satyavānmāril peṭṭavanāṇeṅkil"
        },
        {
            "chapter": 7,
            "verse": 107,
            "text": "appēāḷ mūsā tanṟe vaṭi tāḻeyiṭṭu. appēāḻatā at oru pratyakṣamāya sarppamākunnu"
        },
        {
            "chapter": 7,
            "verse": 108,
            "text": "addēhaṁ tanṟe kai puṟatteṭutt kāṇiccu. appēāḻatā nirīkṣikkunnavarkkellāṁ at veḷḷayāyi kāṇunnu"
        },
        {
            "chapter": 7,
            "verse": 109,
            "text": "phir'aunṟe janatayile pramāṇimār paṟaññu: ivan nalla vivaramuḷḷa jālavidyakkāran tanne"
        },
        {
            "chapter": 7,
            "verse": 110,
            "text": "niṅṅaḷe niṅṅaḷuṭe nāṭṭil ninn puṟattākkānāṇ avan uddēśikkunnat‌. atināl niṅṅaḷkkentāṇ nirdēśikkānuḷḷat‌"
        },
        {
            "chapter": 7,
            "verse": 111,
            "text": "avar (phir'aunēāṭ‌) paṟaññu: ivannuṁ ivanṟe sahēādarannuṁ tāṅkaḷ kuṟacc iṭakeāṭukkuka. nagaraṅṅaḷil cenn viḷiccukūṭṭān āḷukaḷe ayakkukayuṁ ceyyuka"
        },
        {
            "chapter": 7,
            "verse": 112,
            "text": "ellā vivaramuḷḷa jālavidyakkāreyuṁ avar tāṅkaḷuṭe aṭukkal keāṇṭuvaraṭṭe"
        },
        {
            "chapter": 7,
            "verse": 113,
            "text": "jālavidyakkār phir'aunṟe aṭutt vannu. avar paṟaññu: ñaṅṅaḷāṇ jayikkunnavareṅkil ñaṅṅaḷkku nalla pratiphalamuṇṭāyirikkumenn tīrccayāṇallēā"
        },
        {
            "chapter": 7,
            "verse": 114,
            "text": "phir'aun paṟaññu: ate, tīrccayāyuṁ niṅṅaḷ (enṟe aṭukkal) sāmīpyaṁ nalkappeṭunnavaruṭe kūṭṭattilāyirikkukayuṁ ceyyuṁ"
        },
        {
            "chapter": 7,
            "verse": 115,
            "text": "avar paṟaññu: hē, mūsā onnukil nī iṭuka. alleṅkil ñaṅṅaḷākāṁ iṭunnat‌"
        },
        {
            "chapter": 7,
            "verse": 116,
            "text": "mūsā paṟaññu: niṅṅaḷ iṭṭukeāḷḷuka. aṅṅane iṭṭappēāḷ avar āḷukaḷuṭe kaṇṇukeṭṭukayuṁ avarkk bhayamuṇṭākkukayuṁ ceytu. vampicca oru jālavidyayāṇ avar keāṇṭu vannat‌"
        },
        {
            "chapter": 7,
            "verse": 117,
            "text": "mūsāykk nāṁ bēādhanaṁ nalki; nī ninṟe vaṭi iṭṭēkkuka enn‌. appēāḷ ā vaṭiyatā avar kr̥trimamāyi uṇṭākkiyatine viḻuṅṅunnu"
        },
        {
            "chapter": 7,
            "verse": 118,
            "text": "aṅṅane satyaṁ sthirappeṭukayuṁ, avar pravartticcirunnatellāṁ niṣphalamākukayuṁ ceytu"
        },
        {
            "chapter": 7,
            "verse": 119,
            "text": "aṅṅane aviṭe vecc avar parājayappeṭukayuṁ, avar nis'sāranmārāyi māṟukayuṁ ceytu"
        },
        {
            "chapter": 7,
            "verse": 120,
            "text": "avar (ā jālavidyakkār) sāṣṭāṅgan̄ceyyunnavarāyi vīḻukayuṁ ceytu"
        }
    ]
}