{
    "pages": [
        {
            "chapter": 15,
            "verse": 52,
            "text": "Quand ils furent entres chez lui et eurent dit : « Paix ! (Salam) » il dit : « J’ai en verite peur de vous. »"
        },
        {
            "chapter": 15,
            "verse": 53,
            "text": "« N’aie pas peur, dirent-ils, nous t’annoncons l’heureuse naissance d’un garcon dote d’un grand savoir. »"
        },
        {
            "chapter": 15,
            "verse": 54,
            "text": "Il repondit : « M’annoncez-vous cette (heureuse nouvelle) quand m’a deja atteint le grand age? Quelle heureuse nouvelle m’annoncez-vous donc la ? »"
        },
        {
            "chapter": 15,
            "verse": 55,
            "text": "« Nous t’avons annonce la verite. Ne sois donc pas si desespere ! »"
        },
        {
            "chapter": 15,
            "verse": 56,
            "text": "« Et qui pourrait desesperer de la misericorde de son Seigneur, mis a part les egares ? » dit-il"
        },
        {
            "chapter": 15,
            "verse": 57,
            "text": "Et il ajouta : « Que voulez-vous donc, o emissaires (d’Allah) ? »"
        },
        {
            "chapter": 15,
            "verse": 58,
            "text": "« Nous avons ete envoyes vers un peuple de criminels"
        },
        {
            "chapter": 15,
            "verse": 59,
            "text": "hormis la famille de Loth que nous epargnerons tout entiere"
        },
        {
            "chapter": 15,
            "verse": 60,
            "text": "a l’exception de sa femme. » « Nous (Allah) l’avons destinee a etre du nombre des disparus. »"
        },
        {
            "chapter": 15,
            "verse": 61,
            "text": "Lorsque les emissaires vinrent trouver la famille de Loth"
        },
        {
            "chapter": 15,
            "verse": 62,
            "text": "celui-ci leur dit : « Vous nous etes des inconnus. »"
        },
        {
            "chapter": 15,
            "verse": 63,
            "text": "Ils dirent : « Nous sommes plutot venus t’apporter (le chatiment) a propos duquel ils etaient dans le doute"
        },
        {
            "chapter": 15,
            "verse": 64,
            "text": "Nous sommes venus t’apporter la verite, et nous sommes veridiques"
        },
        {
            "chapter": 15,
            "verse": 65,
            "text": "Pars, accompagne de ta famille, lorsqu’une partie de la nuit se sera ecoulee, suis-les en restant a l’arriere, et que personne d’entre vous ne se retourne ! Allez la ou il vous sera ordonne. »"
        },
        {
            "chapter": 15,
            "verse": 66,
            "text": "C’est alors que Nous lui fimes part (a Loth) de Notre decision : tout son peuple sera extermine au point du jour"
        },
        {
            "chapter": 15,
            "verse": 67,
            "text": "Les habitants de la cite[264] vinrent le trouver en jubilant.[265] etaient seduits par la beaute exceptionnelle de ces hotes dont ils ne savaient pas qu’ils etaient des Anges car ces derniers sont arrives chez Loth sous une apparence humaine"
        },
        {
            "chapter": 15,
            "verse": 68,
            "text": "Il leur dit : « Ceux-la sont mes hotes, ne me couvrez pas de honte"
        },
        {
            "chapter": 15,
            "verse": 69,
            "text": "craignez Allah, evitez-moi le deshonneur ! »"
        },
        {
            "chapter": 15,
            "verse": 70,
            "text": "Ils dirent : « Ne t’avons-nous pas defendu (d’accueillir) qui que ce soit au monde ? »"
        }
    ]
}