{
    "pages": [
        {
            "chapter": 30,
            "verse": 33,
            "text": "Saiyaku ga hitobito o nayamasu toki kare-ra wa kaigo shite omoni inoru. Daga kare ga, jihi o kare-ra ni aji wa seru to, tachimachi ichibu no mono wa omoni (soto no kamigami o) haishi"
        },
        {
            "chapter": 30,
            "verse": 34,
            "text": "ware ga ataeta mono o arigataku omowanai yō ni naru. (Wazuka no nengetsu o) kyōraku suruga ī.Daga yagate wakarudearou"
        },
        {
            "chapter": 30,
            "verse": 35,
            "text": "Ware ni hai shite iru mono o shiji suru ken'i o, ware ga kare-ra ni kudashita to demo iu no ka"
        },
        {
            "chapter": 30,
            "verse": 36,
            "text": "Ware ga ningen ni jihi o aji wa seru to, kare-ra wa sore ni kyōki suru. Daga jibun no okonai no tame ni saiyaku ga kudaru to, tachimachi, kare-ra wa zetsubō suru"
        },
        {
            "chapter": 30,
            "verse": 37,
            "text": "Kare-ra wa minai no ka, arrā ga o nozomi no mono ni, kate o mashi, mata herashi nasa reru no o. Hontōni sono nakaniha, shinkō suru mono e no shirushi ga aru"
        },
        {
            "chapter": 30,
            "verse": 38,
            "text": "Sore de kinshin no mono ni, shikarubeki mono o atae yo. Mata hinja to tabibito ni mo. Sore wa, arrā no jigan o motomeru-sha-tachi ni tori, mottomo yoi kotodearu. Korera wa, sakaeru-sha-tachidearu"
        },
        {
            "chapter": 30,
            "verse": 39,
            "text": "Anata gataga rishoku no tame ni, kōri de hito ni kashi ataete mo, arrā no motode wa, nani mo fuenai. Daga arrā no jigan o motomete kisha suru mono ni wa hōshō ga zōka sa reru"
        },
        {
            "chapter": 30,
            "verse": 40,
            "text": "Arrā koso wa, anata gata o tsukuri, fuyō sa re, tsuide shina se, sarani yomigaera se rareru katadearu. Anata gataga (netsuzō shikare ni) hai shita mono no naka, korera no koto no hitotsu demo dekiru mono ga aru ka. Kare ni tatae are. Kare hakare-ra ga haisuru mono no ue ni takaku ora reru"
        },
        {
            "chapter": 30,
            "verse": 41,
            "text": "Ningen no te ga kaseida koto no tame ni, riku ni umi ni kōhai ga mō arawarete iru. Kore wa (arrā ga), kare-ra no okonatta koto no ichibu o ajiwawa se kare-ra o (aku kara) modora seru tamedearu"
        }
    ]
}