{
    "rukus": [
        {
            "chapter": 24,
            "verse": 21,
            "text": "O those who believed! Follow not in the steps of Satan. And whoever follows in the steps of Satan, then, truly, he commands depravity, and that which is unlawful. And if it were not for the grace of God on you and His mercy, none of you would ever be pure in heart, but God makes pure whom He wills. And God is Hearing, Knowing"
        },
        {
            "chapter": 24,
            "verse": 22,
            "text": "Let those imbued with grace not forswear—and those with plenty among you—to give to those imbued with kinship and to the needy and the ones who emigrate in the way of God. And let them pardon and let them overlook. Love you not that God should forgive you? And God is Forgiving, Compassionate"
        },
        {
            "chapter": 24,
            "verse": 23,
            "text": "Truly, those who accuse the ones who are free, unwary, chaste female believers were cursed in the present and the world to come and for them will be a serious punishment"
        },
        {
            "chapter": 24,
            "verse": 24,
            "text": "on a Day when their tongues bear witness against them and their hands and their feet as to what they had been doing"
        },
        {
            "chapter": 24,
            "verse": 25,
            "text": "On that Day God will pay them their account in full, what is their just due. And they will know that God, He is The Clear Truth"
        },
        {
            "chapter": 24,
            "verse": 26,
            "text": "The bad females are for the bad males and the bad males are for the bad females. And who are good females are for who are good males and who are good males are for who are good females. Those are ones declared innocent of what others say. For them is forgiveness and generous provision"
        }
    ]
}