{
    "pages": [
        {
            "chapter": 25,
            "verse": 12,
            "text": "Apabila ia (neraka) melihat mereka dari tempat yang jauh, mereka mendengar suaranya yang gemuruh karena marahnya"
        },
        {
            "chapter": 25,
            "verse": 13,
            "text": "Dan apabila mereka dilemparkan ke tempat yang sempit di neraka dengan dibelenggu, mereka di sana berteriak mengharapkan kebinasaan"
        },
        {
            "chapter": 25,
            "verse": 14,
            "text": "(Akan dikatakan kepada mereka), “Janganlah kamu mengharapkan pada hari ini satu kebinasaan, melainkan harapkanlah kebinasaan yang berulang-ulang.”"
        },
        {
            "chapter": 25,
            "verse": 15,
            "text": "Katakanlah (Muhammad), “Apakah (azab) seperti itu yang baik, atau surga yang kekal yang dijanjikan kepada orang-orang yang bertakwa sebagai balasan, dan tempat kembali bagi mereka?”"
        },
        {
            "chapter": 25,
            "verse": 16,
            "text": "Bagi mereka segala yang mereka kehendaki ada di dalamnya (surga), mereka kekal (di dalamnya). Itulah janji Tuhanmu yang pantas dimohonkan (kepada-Nya)"
        },
        {
            "chapter": 25,
            "verse": 17,
            "text": "Dan (ingatlah) pada hari (ketika) Allah mengumpulkan mereka bersama apa yang mereka sembah selain Allah, lalu Dia berfirman (kepada yang disembah), “Apakah kamu yang menyesatkan hamba-hamba-Ku itu, atau mereka sendirikah yang sesat dari jalan (yang benar)?”"
        },
        {
            "chapter": 25,
            "verse": 18,
            "text": "Mereka (yang disembah itu) menjawab, “Mahasuci Engkau, tidaklah pantas bagi kami mengambil pelindung selain Engkau,*(573) tetapi Engkau telah memberi mereka dan nenek moyang mereka kenikmatan hidup, sehingga mereka melupakan peringatan; dan mereka kaum yang binasa.”"
        },
        {
            "chapter": 25,
            "verse": 19,
            "text": "Maka sungguh, mereka (yang disembah itu) telah mengingkari apa yang kamu katakan, maka kamu tidak akan dapat menolak (azab) dan tidak dapat (pula) menolong (dirimu), dan barang siapa di antara kamu berbuat zalim, niscaya Kami timpakan kepadanya rasa azab yang besar"
        },
        {
            "chapter": 25,
            "verse": 20,
            "text": "Dan Kami tidak mengutus rasul-rasul sebelummu (Muhammad), melainkan mereka pasti memakan makanan dan berjalan di pasar-pasar. Dan Kami jadikan sebagian kamu sebagai cobaan bagi sebagian yang lain. Maukah kamu bersabar? Dan Tuhan kamu Maha Melihat"
        }
    ]
}