{
    "rukus": [
        {
            "chapter": 21,
            "verse": 1,
            "text": "Miyakarani ko manga manosiya so kaphamagitonga kiran a siran na matatago ko kalipat a khitatalikhod"
        },
        {
            "chapter": 21,
            "verse": 2,
            "text": "Daa phakatalingoma kiran a pananadm a phoon ko Kadnan iran a bago, a ba iran di phamamakin´ga a siran na sasablawn iran"
        },
        {
            "chapter": 21,
            "verse": 3,
            "text": "Mabibimban so manga poso iran na inipnanay ran so bitiyara a siran na manga darowaka a: \"Da ko ngkaya inonta na manosiya a lagid iyo; ati zong kano ko balik mata a skano na pkhaylay niyo"
        },
        {
            "chapter": 21,
            "verse": 4,
            "text": "Pitharo (o Mohammad): \"So Kadnan ko na katawan Iyan so katharo ko langit ago so lopa: Go Skaniyan so Pphakan´g a Matao"
        },
        {
            "chapter": 21,
            "verse": 5,
            "text": "Kna, ka pitharo iran a: \"Manga sambar a manga taginpn! Kna, ka pimbabaas iyan oto! Kna, ka skaniyan na pababayok na witi tano niyan sa tanda lagid o kiyasogoa ko miyangaoona"
        },
        {
            "chapter": 21,
            "verse": 6,
            "text": "Daa miyaratiyaya a miyaonaan iran a phagingd, a bininasa Mi skaniyan: Ino siran pharatiyaya siran"
        },
        {
            "chapter": 21,
            "verse": 7,
            "text": "Na da a siyogo Ami ko miyaonaan ka a rowar sa manga mama, a phagilahaman Ami siran na izai niyo so adn a katao niyan o skano na di niyo katawi"
        },
        {
            "chapter": 21,
            "verse": 8,
            "text": "Na da Ami siran snggai sa lawas a di phamangangan ko pangn´ngkn, go kna a ba siran phangakakakal (ko doniya)"
        },
        {
            "chapter": 21,
            "verse": 9,
            "text": "Oriyan iyan na initoman Ami kiran so diyandi, na siyabt Ami siran ago so taw a kabayi Ami, go bininsasa Mi so manga malawani"
        },
        {
            "chapter": 21,
            "verse": 10,
            "text": "Sabnsabnar a tiyoronan Ami skano sa kitab a ndodon so mnang iyo: Ino niyo di pnggdagdaa"
        }
    ]
}